ADB_Easy_Control/__init__.py
ADB_Easy_Control/app_assistant.py
ADB_Easy_Control/data_model.py
ADB_Easy_Control/device_assistant.py
ADB_Easy_Control/key_event.py
ADB_Easy_Control/screen_and_file.py
ADB_Easy_Control/touch_event.py
ADB_Easy_Control/touch_event_withobj.py
ADB_Easy_Control-1.0.1.dist-info/LICENSE
ADB_Easy_Control-1.0.1.dist-info/METADATA
ADB_Easy_Control-1.0.1.dist-info/WHEEL
ADB_Easy_Control-1.0.1.dist-info/top_level.txt
ADB_Easy_Control-1.0.1.dist-info/RECORD
